ovos_skill_wikihow/LICENSE
ovos_skill_wikihow/MANIFEST.in
ovos_skill_wikihow/README.md
ovos_skill_wikihow/__init__.py
ovos_skill_wikihow/requirements.txt
ovos_skill_wikihow/version.py
ovos_skill_wikihow/locale/ca-es/MiscBlacklist.voc
ovos_skill_wikihow/locale/ca-es/Weather.voc
ovos_skill_wikihow/locale/ca-es/howto.failure.dialog
ovos_skill_wikihow/locale/ca-es/howto.intent
ovos_skill_wikihow/locale/ca-es/skill.json
ovos_skill_wikihow/locale/ca-es/step.dialog
ovos_skill_wikihow/locale/ca-es/wikihow.intent
ovos_skill_wikihow/locale/da-dk/howto.failure.dialog
ovos_skill_wikihow/locale/da-dk/howto.intent
ovos_skill_wikihow/locale/da-dk/skill.json
ovos_skill_wikihow/locale/da-dk/step.dialog
ovos_skill_wikihow/locale/da-dk/wikihow.intent
ovos_skill_wikihow/locale/de-de/howto.failure.dialog
ovos_skill_wikihow/locale/de-de/howto.intent
ovos_skill_wikihow/locale/de-de/skill.json
ovos_skill_wikihow/locale/de-de/step.dialog
ovos_skill_wikihow/locale/de-de/wikihow.intent
ovos_skill_wikihow/locale/en-us/MiscBlacklist.voc
ovos_skill_wikihow/locale/en-us/Weather.voc
ovos_skill_wikihow/locale/en-us/howto.failure.dialog
ovos_skill_wikihow/locale/en-us/howto.intent
ovos_skill_wikihow/locale/en-us/skill.json
ovos_skill_wikihow/locale/en-us/step.dialog
ovos_skill_wikihow/locale/en-us/wikihow.intent
ovos_skill_wikihow/locale/eu/howto.failure.dialog
ovos_skill_wikihow/locale/eu/howto.intent
ovos_skill_wikihow/locale/eu/step.dialog
ovos_skill_wikihow/locale/eu/wikihow.intent
ovos_skill_wikihow/locale/gl-es/howto.failure.dialog
ovos_skill_wikihow/locale/gl-es/howto.intent
ovos_skill_wikihow/locale/gl-es/skill.json
ovos_skill_wikihow/locale/gl-es/step.dialog
ovos_skill_wikihow/locale/gl-es/wikihow.intent
ovos_skill_wikihow/locale/it-it/howto.failure.dialog
ovos_skill_wikihow/locale/it-it/howto.intent
ovos_skill_wikihow/locale/it-it/step.dialog
ovos_skill_wikihow/locale/it-it/wikihow.intent
ovos_skill_wikihow/locale/pt-pt/howto.failure.dialog
ovos_skill_wikihow/locale/pt-pt/howto.intent
ovos_skill_wikihow/ovos_skill_wikihow.egg-info/PKG-INFO
ovos_skill_wikihow/ovos_skill_wikihow.egg-info/SOURCES.txt
ovos_skill_wikihow/ovos_skill_wikihow.egg-info/dependency_links.txt
ovos_skill_wikihow/ovos_skill_wikihow.egg-info/entry_points.txt
ovos_skill_wikihow/ovos_skill_wikihow.egg-info/requires.txt
ovos_skill_wikihow/ovos_skill_wikihow.egg-info/top_level.txt
ovos_skill_wikihow-0.3.3.dist-info/LICENSE
ovos_skill_wikihow-0.3.3.dist-info/METADATA
ovos_skill_wikihow-0.3.3.dist-info/WHEEL
ovos_skill_wikihow-0.3.3.dist-info/entry_points.txt
ovos_skill_wikihow-0.3.3.dist-info/top_level.txt
ovos_skill_wikihow-0.3.3.dist-info/RECORD
