Metadata-Version: 2.1
Name: ovos-skill-wikihow
Version: 0.3.3
Summary: search wikihow by voice
Home-page: https://github.com/OpenVoiceOS/ovos-skill-wikihow
Author: OpenVoiceOS
Author-email: jarbasai@mailfence.com
License: Apache2.0
Keywords: ovos skill plugin
License-File: LICENSE
Requires-Dist: pywikihow>=0.5.7
Requires-Dist: ovos-workshop<8.0.0,>=3.4.0a1
Requires-Dist: quebra-frases
